app/__init__.py
app/config.py
app/main.py
app/utils.py
app/converter/__init__.py
app/converter/converter.py
app/converter/regex_heuristics.py
app/converter/tags_heuristics.py
app/converter/wordpress_markdown.py
app/io/__init__.py
app/io/reader.py
app/io/writer.py
docs/conf.py
jekyll_to_hugo-0.0.9.dist-info/METADATA
jekyll_to_hugo-0.0.9.dist-info/WHEEL
jekyll_to_hugo-0.0.9.dist-info/entry_points.txt
jekyll_to_hugo-0.0.9.dist-info/licenses/LICENSE
jekyll_to_hugo-0.0.9.dist-info/RECORD
