Metadata-Version: 2.1
Name: jekyll-to-hugo
Version: 0.0.9
Summary: Python library for converting jekyll md files to Hugo.
Project-URL: Homepage, https://github.com/dnutiu/jekyll-to-hugo
Project-URL: Bug Tracker, https://github.com/dnutiu/jekyll-to-hugo/issues
Author-email: Denis Nutiu <nuculabs@outlook.com>
License-File: LICENSE
Classifier: Environment :: Console
Classifier: License :: OSI Approved :: GNU General Public License v3 or later (GPLv3+)
Classifier: Operating System :: OS Independent
Classifier: Programming Language :: Python
Classifier: Programming Language :: Python :: 3 :: Only
Classifier: Programming Language :: Python :: 3.10
Classifier: Programming Language :: Python :: 3.11
Requires-Python: >=3.10
Requires-Dist: beautifulsoup4<5,>=4.12
Requires-Dist: pydantic<2,>=1.10
Requires-Dist: pyyaml
Requires-Dist: soupsieve<3,>=2.4
Provides-Extra: dev
Requires-Dist: autoflake; extra == 'dev'
Requires-Dist: black; extra == 'dev'
Requires-Dist: isort; extra == 'dev'
Requires-Dist: pytest; extra == 'dev'
Provides-Extra: docs
Requires-Dist: furo==2023.5.20; extra == 'docs'
Requires-Dist: myst-parser; extra == 'docs'
Requires-Dist: sphinx; extra == 'docs'
Requires-Dist: sphinx-autoapi<3,>=2.1.0; extra == 'docs'
